rtl/01_input_spike_index.v
module spike_generator (
  input wire clk,
  input wire reset,
  input wire [63:0] spike_in,
  input wire [63:0] inhib_flag
);

  reg [9:0] time_step;

  always @(posedge clk or posedge reset) begin
    if (reset) begin
      time_step <= 0;
    end else begin
      time_step <= time_step + 1;
      // 디버깅 출력
      $display("Time: %0t, Spike In = %b, Inhibition Flag = %b", $time, spike_in, inhib_flag);
    end
  end

endmodule

tb/tb_01_input_spike_index.v
// tb/tb_01_input_spike_index.v
module tb_spike_generator();

  logic clk = 0;
  logic reset = 0;
  logic [63:0] spike_in;

  // spike 데이터를 저장할 배열
  reg [63:0] spike_data [0:1023]; // 최대 1024 timestep

  integer i;

  // DUT 연결
  spike_generator uut (
    .clk(clk),
    .reset(reset),
    .spike_in(spike_in)
  );

  // 클럭 생성: 10ns 주기
  always #5 clk = ~clk;

  initial begin
    $dumpfile("wave.vcd");
    $dumpvars(0, tb_spike_generator);

    // spike 파일 읽기 (2진수 포맷)
    $readmemb("tb/spike_input.txt", spike_data);

    // 초기화
    reset = 1; #10; reset = 0;

    // spike 입력
    for (i = 0; i < 10; i = i + 1) begin
      spike_in = spike_data[i];
      #10;
    end

    $finish;
  end

endmodule

wave.vcd
$date
	Wed Aug  6 13:48:13 2025
$end
$version
	Icarus Verilog
$end
$timescale
	1s
$end
$scope module tb_spike_generator $end
$var reg 1 ! clk $end
$var reg 1 " reset $end
$var reg 64 # spike_in [63:0] $end
$var integer 32 $ i [31:0] $end
$scope module uut $end
$var wire 1 ! clk $end
$var wire 64 % inhib_flag [63:0] $end
$var wire 1 " reset $end
$var wire 64 & spike_in [63:0] $end
$var reg 10 ' time_step [9:0] $end
$upscope $end
$upscope $end
$enddefinitions $end
$comment Show the parameter values. $end
$dumpall
$end
#0
$dumpvars
b0 '
bx &
bz %
bx $
bx #
1"
0!
$end
#5
1!
#10
0!
b1111101010110010101001001000101110100110101001100010101001110001 #
b1111101010110010101001001000101110100110101001100010101001110001 &
b0 $
0"
#15
b1 '
1!
#20
0!
b10010111011111101110010110010110100111111001010010110000110111 #
b10010111011111101110010110010110100111111001010010110000110111 &
b1 $
#25
b10 '
1!
#30
0!
b11010100010101100011011101010010111100101100100110100001101010 #
b11010100010101100011011101010010111100101100100110100001101010 &
b10 $
#35
b11 '
1!
#40
0!
b100101111011101111011111010011101101111101001010000000110101100 #
b100101111011101111011111010011101101111101001010000000110101100 &
b11 $
#45
b100 '
1!
#50
0!
b1011001001101110111010110101111111111000101111111010001010011011 #
b1011001001101110111010110101111111111000101111111010001010011011 &
b100 $
#55
b101 '
1!
#60
0!
b1001111001011010100000000110000001100110101100011010001111110101 #
b1001111001011010100000000110000001100110101100011010001111110101 &
b101 $
#65
b110 '
1!
#70
0!
b1010101010001000011000010111100110110100011001101000110000010101 #
b1010101010001000011000010111100110110100011001101000110000010101 &
b110 $
#75
b111 '
1!
#80
0!
b101100010100010011000001000011000100011110100101101011000110110 #
b101100010100010011000001000011000100011110100101101011000110110 &
b111 $
#85
b1000 '
1!
#90
0!
b1011101001111100101011011101101010011011101000101111110000001011 #
b1011101001111100101011011101101010011011101000101111110000001011 &
b1000 $
#95
b1001 '
1!
#100
0!
b1011101000100110011010111001010010011100000000100110011010011010 #
b1011101000100110011010111001010010011100000000100110011010011010 &
b1001 $
#105
b1010 '
1!
#110
0!
b1010 $
