rtl/01_input_spike_index.v
module spike_generator (
  input wire clk,
  input wire reset,
  input wire [63:0] spike_in
);

  reg [3:0] time_step;

  always @(posedge clk or posedge reset) begin
    if (reset) begin
      time_step <= 0;
    end else begin
      time_step <= time_step + 1;
      // 현재 spike 값 출력 (디버깅용)
      $display("Time: %0t, Spike In = %b", $time, spike_in);
    end
  end

endmodule

tb/tb_01_input_spike_index.v
// tb/tb_01_input_spike_index.v
module tb_spike_generator();

  logic clk = 0;
  logic reset = 0;
  logic [63:0] spike_in;

  // spike 데이터를 저장할 배열
  reg [63:0] spike_data [0:1023]; // 최대 1024 timestep

  integer i;

  // DUT 연결
  spike_generator uut (
    .clk(clk),
    .reset(reset),
    .spike_in(spike_in)
  );

  // 클럭 생성: 10ns 주기
  always #5 clk = ~clk;

  initial begin
    $dumpfile("wave.vcd");
    $dumpvars(0, tb_spike_generator);

    // spike 파일 읽기 (2진수 포맷)
    $readmemb("tb/spike_input.txt", spike_data);

    // 초기화
    reset = 1; #10; reset = 0;

    // spike 입력
    for (i = 0; i < 10; i = i + 1) begin
      spike_in = spike_data[i];
      #10;
    end

    $finish;
  end

endmodule

wave.vcd
$date
	Wed Aug  6 12:31:30 2025
$end
$version
	Icarus Verilog
$end
$timescale
	1s
$end
$scope module tb_spike_generator $end
$var reg 1 ! clk $end
$var reg 1 " reset $end
$var reg 64 # spike_in [63:0] $end
$var integer 32 $ i [31:0] $end
$scope module uut $end
$var wire 1 ! clk $end
$var wire 1 " reset $end
$var wire 64 % spike_in [63:0] $end
$var reg 4 & time_step [3:0] $end
$upscope $end
$upscope $end
$enddefinitions $end
$comment Show the parameter values. $end
$dumpall
$end
#0
$dumpvars
b0 &
bx %
bx $
bx #
1"
0!
$end
#5
1!
#10
0!
b1111100100001000001010101010110101100111100011000001011011100101 #
b1111100100001000001010101010110101100111100011000001011011100101 %
b0 $
0"
#15
b1 &
1!
#20
0!
b110011010101000010001010010011110101000000000110000111001100000 #
b110011010101000010001010010011110101000000000110000111001100000 %
b1 $
#25
b10 &
1!
#30
0!
b1001010100011011110011001011110001101110010101110011011011 #
b1001010100011011110011001011110001101110010101110011011011 %
b10 $
#35
b11 &
1!
#40
0!
b1000011100000000000110101110100011100010001010011001100010001001 #
b1000011100000000000110101110100011100010001010011001100010001001 %
b11 $
#45
b100 &
1!
#50
0!
b11010110111010100011111110001001000011111000101111111101010010 #
b11010110111010100011111110001001000011111000101111111101010010 %
b100 $
#55
b101 &
1!
#60
0!
b1001011001001000011101111110110010101001111101010110000101010010 #
b1001011001001000011101111110110010101001111101010110000101010010 %
b101 $
#65
b110 &
1!
#70
0!
b1110100011010100011010001010101100101101011100000110011110000111 #
b1110100011010100011010001010101100101101011100000110011110000111 %
b110 $
#75
b111 &
1!
#80
0!
b1000001110000001101100111011010001111111110101101000000001110110 #
b1000001110000001101100111011010001111111110101101000000001110110 %
b111 $
#85
b1000 &
1!
#90
0!
b1100001010101101011011000101001110000010010110110001100100001101 #
b1100001010101101011011000101001110000010010110110001100100001101 %
b1000 $
#95
b1001 &
1!
#100
0!
b1101111011111001000011010011011101110100110011110110010011010101 #
b1101111011111001000011010011011101110100110011110110010011010101 %
b1001 $
#105
b1010 &
1!
#110
0!
b1010 $
